imgtk/__init__.py
imgtk/cli.py
imgtk/filters.py
imgtk/img.py
imgtk/modifiers.py
imgtk_python-0.0.8.dist-info/LICENSE
imgtk_python-0.0.8.dist-info/METADATA
imgtk_python-0.0.8.dist-info/WHEEL
imgtk_python-0.0.8.dist-info/entry_points.txt
imgtk_python-0.0.8.dist-info/top_level.txt
imgtk_python-0.0.8.dist-info/RECORD
