Metadata-Version: 2.1
Name: imgtk-python
Version: 0.0.8
Home-page: https://github.com/zigai/py-pipeline
Author: Žiga Ivanšek
Author-email: ziga.ivansek@gmail.com
License: MIT
Classifier: Programming Language :: Python
Classifier: Programming Language :: Python :: 3.10
Classifier: Programming Language :: Python :: 3 :: Only
Classifier: Topic :: Software Development :: Libraries :: Python Modules
License-File: LICENSE
Requires-Dist: Pillow>=10.0.1
Requires-Dist: pytesseract==0.3.10
Requires-Dist: stdl>=0.5.5
Requires-Dist: pypeline-python>=0.1.8
